sweeper/__init__.py
sweeper/__main__.py
sweeper/address_parser.py
sweeper/backup.py
sweeper/config.py
sweeper/report.py
sweeper/street_types.json
sweeper/utilities.py
sweeper/workspace_info.py
sweeper/sweepers/UseLimitations.html
sweeper/sweepers/__init__.py
sweeper/sweepers/addresses.py
sweeper/sweepers/base.py
sweeper/sweepers/duplicates.py
sweeper/sweepers/empties.py
sweeper/sweepers/invalids.py
sweeper/sweepers/metadata.py
ugrc_sweeper-2.0.6.dist-info/licenses/LICENSE
ugrc_sweeper-2.0.6.dist-info/METADATA
ugrc_sweeper-2.0.6.dist-info/WHEEL
ugrc_sweeper-2.0.6.dist-info/entry_points.txt
ugrc_sweeper-2.0.6.dist-info/top_level.txt
ugrc_sweeper-2.0.6.dist-info/RECORD
