Metadata-Version: 2.4
Name: ugrc-sweeper
Version: 2.0.6
Summary: CLI tool for making good data
Home-page: https://github.com/agrc/sweeper
Author: UGRC
Author-email: ugrc-developers@utah.gov
License: MIT
Classifier: Development Status :: 5 - Production/Stable
Classifier: Intended Audience :: Developers
Classifier: License :: OSI Approved :: MIT License
Classifier: Operating System :: Unix
Classifier: Operating System :: POSIX
Classifier: Operating System :: Microsoft :: Windows
Classifier: Programming Language :: Python
Classifier: Programming Language :: Python :: 3 :: Only
Classifier: Topic :: Utilities
Requires-Python: >=3
License-File: LICENSE
Requires-Dist: ugrc-supervisor==3.*
Requires-Dist: agrc-usaddress==0.*
Requires-Dist: beautifulsoup4==4.*
Requires-Dist: docopt==0.*
Requires-Dist: html5lib==1.*
Requires-Dist: xxhash==3.*
Provides-Extra: tests
Requires-Dist: pytest-cov<8,>=6; extra == "tests"
Requires-Dist: pytest-instafail==0.5.*; extra == "tests"
Requires-Dist: pytest-mock==3.*; extra == "tests"
Requires-Dist: pytest-watch==4.*; extra == "tests"
Requires-Dist: pytest==8.*; extra == "tests"
Requires-Dist: ruff==0.*; extra == "tests"
Dynamic: author
Dynamic: author-email
Dynamic: classifier
Dynamic: description
Dynamic: description-content-type
Dynamic: home-page
Dynamic: license
Dynamic: license-file
Dynamic: provides-extra
Dynamic: requires-dist
Dynamic: requires-python
Dynamic: summary
